[
    {
        "id":"1",
        "logo":"./logo-viacomcbs.png"
    },
    {
        "id":"2",
        "logo":"./logo-tradedesk.png"
    },
    {
        "id":"3",
        "logo":"./logo-seismic.png"
    },
    {
        "id":"4",
        "logo":"./logo-pluralsight.png"
    },
    {
        "id":"5",
        "logo":"./logo-mindshare-1.png"
    },
    {
        "id":"6",
        "logo":"./logo-kraft-heinz.png"
    },
    {
        "id":"7",
        "logo":"./logo-jamf-1.png"
    },
    {
        "id":"8",
        "logo":"./logo-invision.png"
    },
    {
        "id":"9",
        "logo":"./logo-goldman-sachs.png"
    },
    {
        "id":"10",
        "logo":"./logo-github.png"
    },
    {
        "id":"11",
        "logo":"./logo-coursera.png"
    },
    {
        "id":"12",
        "logo":"./logo-cloudflare.png"
    },
    {
        "id":"13",
        "logo":"./logo-casper-1.png"
    }
    
]